_quickjs.cpython-310-x86_64-linux-gnu.so
quickjs/__init__.py
quickjs-1.19.4.dist-info/LICENSE
quickjs-1.19.4.dist-info/METADATA
quickjs-1.19.4.dist-info/RECORD
quickjs-1.19.4.dist-info/top_level.txt
quickjs-1.19.4.dist-info/WHEEL
