Metadata-Version: 2.1
Name: quickjs
Version: 1.19.4
Summary: Wrapping the quickjs C library.
Home-page: https://github.com/PetterS/quickjs
Author: Petter Strandmark
Author-email: petter.strandmark@gmail.com
Maintainer: Quentin Wenger
Maintainer-email: matpi@protonmail.ch
License-File: LICENSE
